prometheus_kafka_consumer_group_exporter/__init__.py
prometheus_kafka_consumer_group_exporter/__main__.py
prometheus_kafka_consumer_group_exporter/collectors.py
prometheus_kafka_consumer_group_exporter/fetch_jobs.py
prometheus_kafka_consumer_group_exporter/parsing.py
prometheus_kafka_consumer_group_exporter/scheduler.py
prometheus_kafka_consumer_group_exporter-0.5.5.dist-info/LICENSE
prometheus_kafka_consumer_group_exporter-0.5.5.dist-info/METADATA
prometheus_kafka_consumer_group_exporter-0.5.5.dist-info/WHEEL
prometheus_kafka_consumer_group_exporter-0.5.5.dist-info/entry_points.txt
prometheus_kafka_consumer_group_exporter-0.5.5.dist-info/top_level.txt
prometheus_kafka_consumer_group_exporter-0.5.5.dist-info/RECORD
