Metadata-Version: 2.1
Name: prometheus-kafka-consumer-group-exporter
Version: 0.5.5
Summary: Kafka consumer group Prometheus exporter
Home-page: https://github.com/Braedon/prometheus-kafka-consumer-group-exporter
Author: Braedon Vickers
Author-email: braedon.vickers@gmail.com
License: MIT
Keywords: monitoring prometheus exporter kafka consumer group
Platform: UNKNOWN
Classifier: Development Status :: 4 - Beta
Classifier: Intended Audience :: Developers
Classifier: Intended Audience :: System Administrators
Classifier: Topic :: System :: Monitoring
Classifier: License :: OSI Approved :: MIT License
Classifier: Programming Language :: Python :: 3
Classifier: Programming Language :: Python :: 3.4
Classifier: Programming Language :: Python :: 3.5
Classifier: Programming Language :: Python :: 3.6
Classifier: Programming Language :: Python :: 3.7
Requires-Dist: kafka-python (!=1.4.5,!=1.4.6,>=1.3)
Requires-Dist: jog
Requires-Dist: prometheus-client (>=0.6.0)
Requires-Dist: javaproperties
